{"library":"ACM Hypertext 2022","year":"2022","version":1.3,"user":"Andrew Thompson","generator":"objgen.com","generatedOn":"2024-07-29T19:07:00.000Z","documents":[{"title":"Towards Proactively Forecasting Sentence-Specific Information Popularity within Online News Documents","author":["Sayar Ghosh Roy","Anshul Padhi","Risubh Jain","Manish Gupta","Vasudeva Varma"],"year":"2022","type":"long","source":"./_ref/htconference/2022/3511095.3531268.html","customData":[{"isFavorite":false,"keywords":["Sentence Popularity Forecasting","Sentence Salience Prediction","Supervised Transfer Learning"],"keywordsPosY":["0.000","0.000","0.000"],"keywordsRotY":["0.000","0.000","0.000"],"keywordsDist":["0.000","0.000","0.000"],"names":["Sayar Ghosh Roy","Anshul Padhi","Risubh Jain","Manish Gupta","Vasudeva Varma"],"namesPosY":["0.000","0.000","0.000","0.000","0.000"],"namesRotY":["0.000","0.000","0.000","0.000","0.000"],"namesDist":["0.000","0.000","0.000","0.000","0.000"],"titlePosY":"0.000","titleRotY":"0.000","titleDist":"0.000"}]},{"title":"Learning to Adapt Domain Shifts of Moral Values via Instance Weighting","author":["Xiaolei Huang","Alexandra Wormley","Adam Cohen"],"year":"2022","type":"short","source":"./_ref/htconference/2022/3511095.3531269.html","customData":[{"isFavorite":false,"keywords":["morality","moral values","classification","domain variation","adaptation","instant weighting"],"keywordsPosY":["0.000","0.000","0.000","0.000","0.000","0.000"],"keywordsRotY":["0.000","0.000","0.000","0.000","0.000","0.000"],"keywordsDist":["0.000","0.000","0.000","0.000","0.000","0.000"],"names":["Xiaolei Huang","Alexandra Wormley","Adam Cohen"],"namesPosY":["0.000","0.000","0.000"],"namesRotY":["0.000","0.000","0.000"],"namesDist":["0.000","0.000","0.000"],"titlePosY":"0.000","titleRotY":"0.000","titleDist":"0.000"}]},{"title":"Links Of Darkness: Hypertext And Horror","author":["Mark Bernstein","Stee McMorris"],"year":"2022","type":"poster","source":"./_ref/htconference/2022/3511095.3531270.html","customData":[{"isFavorite":false,"keywords":["Hypertext","Links","Horror","World Wide Web","Literary Hypertext"],"keywordsPosY":["0.000","0.000","0.000","0.000","0.000"],"keywordsRotY":["0.000","0.000","0.000","0.000","0.000"],"keywordsDist":["0.000","0.000","0.000","0.000","0.000"],"names":["Mark Bernstein","Stee McMorris"],"namesPosY":["0.000","0.000"],"namesRotY":["0.000","0.000"],"namesDist":["0.000","0.000"],"titlePosY":"0.000","titleRotY":"0.000","titleDist":"0.000"}]},{"title":"Hypertext's meta-history: Documenting in-conference citations, authors and keyword data, 1987-2021","author":["Mark Anderson","David Millard"],"year":"2022","type":"workshop","source":"./_ref/htconference/2022/3511095.3531271.html","customData":[{"isFavorite":true,"keywords":["hypertext","knowledge management","metadata","citation networks","links","linkbases","gender","Tinderbox","dataset","keywords","keywording","visualisation","analysis"],"keywordsPosY":["0.000","0.000","0.000","0.000","0.000","0.000","0.000","0.000","0.000","0.000","0.000","0.000","0.000"],"keywordsRotY":["0.000","0.000","0.000","0.000","0.000","0.000","0.000","0.000","0.000","0.000","0.000","0.000","0.000"],"keywordsDist":["0.000","0.000","0.000","0.000","0.000","0.000","0.000","0.000","0.000","0.000","0.000","0.000","0.000"],"names":["Mark Anderson","David Millard"],"namesPosY":["0.000","0.000"],"namesRotY":["0.000","0.000"],"namesDist":["0.000","0.000"],"titlePosY":"0.000","titleRotY":"0.000","titleDist":"0.000"}]},{"title":"The Impact of Non-Verbalization in Think-Aloud: Understanding Knowledge Gain Indicators Considering Think-Aloud Web Searches","author":["Marcelo Tibau","Sean Wolfgand","Matsui Siqueira","Bernardo Pereira Nunes"],"year":"2022","type":"short","source":"./_ref/htconference/2022/3511095.3531272.html","customData":[{"isFavorite":false,"keywords":["Think-aloud protocols","online information searching strategy","knowledge gain indicators","hypertext theory","Web search"],"keywordsPosY":["0.000","0.000","0.000","0.000","0.000"],"keywordsRotY":["0.000","0.000","0.000","0.000","0.000"],"keywordsDist":["0.000","0.000","0.000","0.000","0.000"],"names":["Marcelo Tibau","Sean Wolfgand","Matsui Siqueira","Bernardo Pereira Nunes"],"namesPosY":["0.000","0.000","0.000","0.000"],"namesRotY":["0.000","0.000","0.000","0.000"],"namesDist":["0.000","0.000","0.000","0.000"],"titlePosY":"0.000","titleRotY":"0.000","titleDist":"0.000"}]},{"title":"Enabling Convenient Online Collaborative Writing for Low Vision Screen Magnifier Users","author":["Hae-Na Lee","Yash Prakash","Mohan Sunkara","I.V. Ramakrishnan","Vikas Ashok"],"year":"2022","type":"poster","source":"./_ref/htconference/2022/3511095.3531274.html","customData":[{"isFavorite":false,"keywords":["Online Collaborative Writing","Low Vision","Screen Magnifier","Visual Impairment","Accessibility","Assistive Technology"],"keywordsPosY":["0.000","0.000","0.000","0.000","0.000","0.000"],"keywordsRotY":["0.000","0.000","0.000","0.000","0.000","0.000"],"keywordsDist":["0.000","0.000","0.000","0.000","0.000","0.000"],"names":["Hae-Na Lee","Yash Prakash","Mohan Sunkara","I.V. Ramakrishnan","Vikas Ashok"],"namesPosY":["0.000","0.000","0.000","0.000","0.000"],"namesRotY":["0.000","0.000","0.000","0.000","0.000"],"namesDist":["0.000","0.000","0.000","0.000","0.000"],"titlePosY":"0.000","titleRotY":"0.000","titleDist":"0.000"}]},{"title":"Kronecker Decomposition for Knowledge Graph Embeddings","author":["Caglar Demir","Julian Lienen","Axel-Cyrille","Ngonga Ngomo"],"year":"2022","type":"long","source":"./_ref/htconference/2022/3511095.3531276.html","customData":[{"isFavorite":false,"keywords":["Knowledge Graph Embedding","Kronecker Decomposition","Link Prediction"],"keywordsPosY":["0.000","0.000","0.000"],"keywordsRotY":["0.000","0.000","0.000"],"keywordsDist":["0.000","0.000","0.000"],"names":["Caglar Demir","Julian Lienen","Axel-Cyrille","Ngonga Ngomo"],"namesPosY":["0.000","0.000","0.000","0.000"],"namesRotY":["0.000","0.000","0.000","0.000"],"namesDist":["0.000","0.000","0.000","0.000"],"titlePosY":"0.000","titleRotY":"0.000","titleDist":"0.000"}]},{"title":"Data Bootstrapping Approaches to Improve Low Resource Abusive Language Detection for Indic Languages","author":["Mithun Das","Somnath Banerjee","Animesh Mukherjee"],"year":"2022","type":"workshop","source":"./_ref/htconference/2022/3511095.3531277.html","customData":[{"isFavorite":false,"keywords":["Abusive language","multilingual","detection","social media"],"keywordsPosY":["0.000","0.000","0.000","0.000"],"keywordsRotY":["0.000","0.000","0.000","0.000"],"keywordsDist":["0.000","0.000","0.000","0.000"],"names":["Mithun Das","Somnath Banerjee","Animesh Mukherjee"],"namesPosY":["0.000","0.000","0.000"],"namesRotY":["0.000","0.000","0.000"],"namesDist":["0.000","0.000","0.000"],"titlePosY":"0.000","titleRotY":"0.000","titleDist":"0.000"}]},{"title":"The Magic of Carousels: Single vs. Multi-List Recommender Systems","author":["Behnam Rahdari","Branislav Kveton","Peter Brusilovsky"],"year":"2022","type":"workshop","source":"./_ref/htconference/2022/3511095.3531278.html","customData":[{"isFavorite":false,"keywords":["Recommender Systems","Carousel-based interface","Human-AI collaboration","Navigability","Click Models"],"keywordsPosY":["0.000","0.000","0.000","0.000","0.000"],"keywordsRotY":["0.000","0.000","0.000","0.000","0.000"],"keywordsDist":["0.000","0.000","0.000","0.000","0.000"],"names":["Behnam Rahdari","Branislav Kveton","Peter Brusilovsky"],"namesPosY":["0.000","0.000","0.000"],"namesRotY":["0.000","0.000","0.000"],"namesDist":["0.000","0.000","0.000"],"titlePosY":"0.000","titleRotY":"0.000","titleDist":"0.000"}]},{"title":"Cross-Lingual Query-Based Summarization of Crisis-Related Social Media: An Abstractive Approach Using Transformers","author":["Fedor Vitiugin","Carlos Castillo"],"year":"2022","type":"short","source":"./_ref/htconference/2022/3511095.3531279.html","customData":[{"isFavorite":false,"keywords":["abstractive summarization","multilingual retrieval","social media","emergency management"],"keywordsPosY":["0.000","0.000","0.000","0.000"],"keywordsRotY":["0.000","0.000","0.000","0.000"],"keywordsDist":["0.000","0.000","0.000","0.000"],"names":["Fedor Vitiugin","Carlos Castillo"],"namesPosY":["0.000","0.000"],"namesRotY":["0.000","0.000"],"namesDist":["0.000","0.000"],"titlePosY":"0.000","titleRotY":"0.000","titleDist":"0.000"}]},{"title":"The Effect of Recommendation Source and Justification on Professional Development Recommendations for High School Teachers","author":["Lijie Guo","Christopher Flathmann","Reza Anaraky","Nathan McNeese","Bart Knijnenburg"],"year":"2022","type":"long","source":"./_ref/htconference/2022/3511095.3531280.html","customData":[{"isFavorite":false,"keywords":["recommender systems","professional development","algorithm aversion","justification"],"keywordsPosY":["0.000","0.000","0.000","0.000"],"keywordsRotY":["0.000","0.000","0.000","0.000"],"keywordsDist":["0.000","0.000","0.000","0.000"],"names":["Lijie Guo","Christopher Flathmann","Reza Anaraky","Nathan McNeese","Bart Knijnenburg"],"namesPosY":["0.000","0.000","0.000","0.000","0.000"],"namesRotY":["0.000","0.000","0.000","0.000","0.000"],"namesDist":["0.000","0.000","0.000","0.000","0.000"],"titlePosY":"0.000","titleRotY":"0.000","titleDist":"0.000"}]},{"title":"Exploring the Feasibility of Crowd-Powered Decomposition of Complex User Questions in Text-to-SQL Tasks","author":["Sara Salimzadeh","Ujwal Gadiraju","Claudia Hauff","Arie van Deursen"],"year":"2022","type":"short","source":"./_ref/htconference/2022/3511095.3531282.html","customData":[{"isFavorite":false,"keywords":["Text-to-SQL","Semantic Parsing","Natural Language Interface to Databases","Crowdsourcing","Human Computation","Corpus Annotation"],"keywordsPosY":["0.000","0.000","0.000","0.000","0.000","0.000"],"keywordsRotY":["0.000","0.000","0.000","0.000","0.000","0.000"],"keywordsDist":["0.000","0.000","0.000","0.000","0.000","0.000"],"names":["Sara Salimzadeh","Ujwal Gadiraju","Claudia Hauff","Arie van Deursen"],"namesPosY":["0.000","0.000","0.000","0.000"],"namesRotY":["0.000","0.000","0.000","0.000"],"namesDist":["0.000","0.000","0.000","0.000"],"titlePosY":"0.000","titleRotY":"0.000","titleDist":"0.000"}]},{"title":"Characterizing Vaccination Movements on YouTube in the United States and Brazil","author":["Marcelo Sartori Locatelli","Josemar Caetano","Wagner Meira Jr.","Virgilio Almeida"],"year":"2022","type":"poster","source":"./_ref/htconference/2022/3511095.3531283.html","customData":[{"isFavorite":false,"keywords":["social media","vaccination movements","textual analysis"],"keywordsPosY":["0.000","0.000","0.000"],"keywordsRotY":["0.000","0.000","0.000"],"keywordsDist":["0.000","0.000","0.000"],"names":["Marcelo Sartori Locatelli","Josemar Caetano","Wagner Meira Jr.","Virgilio Almeida"],"namesPosY":["0.000","0.000","0.000","0.000"],"namesRotY":["0.000","0.000","0.000","0.000"],"namesDist":["0.000","0.000","0.000","0.000"],"titlePosY":"0.000","titleRotY":"0.000","titleDist":"0.000"}]},{"title":"SpaceE: Knowledge Graph Embedding by Relational Linear Transformation in the Entity Space","author":["Jinxing Yu","Yunfeng Cai","Mingming Sun","Ping Li"],"year":"2022","type":"workshop","source":"./_ref/htconference/2022/3511095.3531284.html","customData":[{"isFavorite":false,"keywords":["Knowledge Graph Embedding","Link Prediction","Non-Injective Relations"],"keywordsPosY":["0.000","0.000","0.000"],"keywordsRotY":["0.000","0.000","0.000"],"keywordsDist":["0.000","0.000","0.000"],"names":["Jinxing Yu","Yunfeng Cai","Mingming Sun","Ping Li"],"namesPosY":["0.000","0.000","0.000","0.000"],"namesRotY":["0.000","0.000","0.000","0.000"],"namesDist":["0.000","0.000","0.000","0.000"],"titlePosY":"0.000","titleRotY":"0.000","titleDist":"0.000"}]},{"title":"Is there an Author in this Labyrinth? Hypertext Fiction and Farrell's Textual Fallacy","author":["Sam Brooker"],"year":"2022","type":"long","source":"./_ref/htconference/2022/3511095.3531285.html","customData":[{"isFavorite":false,"keywords":["Hypertext","Links","Literary Hypertext"],"keywordsPosY":["0.000","0.000","0.000"],"keywordsRotY":["0.000","0.000","0.000"],"keywordsDist":["0.000","0.000","0.000"],"names":["Sam Brooker"],"namesPosY":["0.000"],"namesRotY":["0.000"],"namesDist":["0.000"],"titlePosY":"0.000","titleRotY":"0.000","titleDist":"0.000"}]},{"title":"The Effects of Spatial Visualization versus Ranked Lists on Quality, Time Efficiency, and Interaction","author":["Daniel Robner","Claus Atzenbeck","Tom Gross"],"year":"2022","type":"short","source":"./_ref/htconference/2022/3511095.3531286.html","customData":[{"isFavorite":false,"keywords":["information retrieval","exploratory search","spatial hypertext","spatial layout","ranked list","user study"],"keywordsPosY":["0.000","0.000","0.000","0.000","0.000","0.000"],"keywordsRotY":["0.000","0.000","0.000","0.000","0.000","0.000"],"keywordsDist":["0.000","0.000","0.000","0.000","0.000","0.000"],"names":["Daniel Robner","Claus Atzenbeck","Tom Gross"],"namesPosY":["0.000","0.000","0.000"],"namesRotY":["0.000","0.000","0.000"],"namesDist":["0.000","0.000","0.000"],"titlePosY":"0.000","titleRotY":"0.000","titleDist":"0.000"}]},{"title":"ADAGIO — Automated Data Augmentation of Knowledge Graphs Using Multi-expression Learning","author":["Kevin Dressler","Mohamed Ahmed Sherif","Axel-Cyrille Ngonga Ngomo"],"year":"2022","type":"short","source":"./_ref/htconference/2022/3511095.3531287.html","customData":[{"isFavorite":false,"keywords":["Knowledge graphs","Data augmentation","Data integration","Machine learning","Genetic programming","Multi expression programming"],"keywordsPosY":["0.000","0.000","0.000","0.000","0.000","0.000"],"keywordsRotY":["0.000","0.000","0.000","0.000","0.000","0.000"],"keywordsDist":["0.000","0.000","0.000","0.000","0.000","0.000"],"names":["Kevin Dressler","Mohamed Ahmed Sherif","Axel-Cyrille Ngonga Ngomo"],"namesPosY":["0.000","0.000","0.000"],"namesRotY":["0.000","0.000","0.000"],"namesDist":["0.000","0.000","0.000"],"titlePosY":"0.000","titleRotY":"0.000","titleDist":"0.000"}]},{"title":"Characterizing Sponsored Content in Facebook and Instagram","author":["Emanuelle Azevedo Martins","Isadora Salles","Fabricio Benevenuto","Olga Goussevskaia"],"year":"2022","type":"long","source":"./_ref/htconference/2022/3511095.3531289.html","customData":[{"isFavorite":false,"keywords":["Social network analysis","sponsored content","influencer marketing","Instagram","Facebook"],"keywordsPosY":["0.000","0.000","0.000","0.000","0.000"],"keywordsRotY":["0.000","0.000","0.000","0.000","0.000"],"keywordsDist":["0.000","0.000","0.000","0.000","0.000"],"names":["Emanuelle Azevedo Martins","Isadora Salles","Fabricio Benevenuto","Olga Goussevskaia"],"namesPosY":["0.000","0.000","0.000","0.000"],"namesRotY":["0.000","0.000","0.000","0.000"],"namesDist":["0.000","0.000","0.000","0.000"],"titlePosY":"0.000","titleRotY":"0.000","titleDist":"0.000"}]},{"title":"SIDEWAYS-2022 @ HT-2022: 7th International Workshop on Social Media World Sensors","author":["Luigi Di Caro","Claudio Schifanella","Mario Cataldi"],"year":"2022","type":"poster","source":"./_ref/htconference/2022/3511095.3532573.html","customData":[{"isFavorite":false,"keywords":["social media","sensors","topic detection","data mining"],"keywordsPosY":["0.000","0.000","0.000","0.000"],"keywordsRotY":["0.000","0.000","0.000","0.000"],"keywordsDist":["0.000","0.000","0.000","0.000"],"names":["Luigi Di Caro","Claudio Schifanella","Mario Cataldi"],"namesPosY":["0.000","0.000","0.000"],"namesRotY":["0.000","0.000","0.000"],"namesDist":["0.000","0.000","0.000"],"titlePosY":"0.000","titleRotY":"0.000","titleDist":"0.000"}]},{"title":"OASIS’22: 2nd International Workshop on Open Challenges in Online Social Networks","author":["Barbara Guidi","Laura Ricci"],"year":"2022","type":"workshop","source":"./_ref/htconference/2022/3511095.3532574.html","customData":[{"isFavorite":false,"keywords":["Social Networks and Media: analysis and mining","Decentralization","Blockchain","AI for Social Media"],"keywordsPosY":["0.000","0.000","0.000","0.000"],"keywordsRotY":["0.000","0.000","0.000","0.000"],"keywordsDist":["0.000","0.000","0.000","0.000"],"names":["Barbara Guidi","Laura Ricci"],"namesPosY":["0.000","0.000"],"namesRotY":["0.000","0.000"],"namesDist":["0.000","0.000"],"titlePosY":"0.000","titleRotY":"0.000","titleDist":"0.000"}]},{"title":"5th Workshop on Human Factors in Hypertext (HUMAN ’22)","author":["Claus Atzenbeck","Jessica Rubart"],"year":"2022","type":"workshop","source":"./_ref/htconference/2022/3511095.3532575.html","customData":[{"isFavorite":false,"keywords":["hypertext","hypermedia","human factors","augmentation","user-centric","user interfaces","user interaction","cognitive aspects","collaboration","information structuring","communication","decision making","annotation","digital humanities","adaptive hypertext","intercultural aspects"],"keywordsPosY":["0.000","0.000","0.000","0.000","0.000","0.000","0.000","0.000","0.000","0.000","0.000","0.000","0.000","0.000","0.000","0.000"],"keywordsRotY":["0.000","0.000","0.000","0.000","0.000","0.000","0.000","0.000","0.000","0.000","0.000","0.000","0.000","0.000","0.000","0.000"],"keywordsDist":["0.000","0.000","0.000","0.000","0.000","0.000","0.000","0.000","0.000","0.000","0.000","0.000","0.000","0.000","0.000","0.000"],"names":["Claus Atzenbeck","Jessica Rubart"],"namesPosY":["0.000","0.000"],"namesRotY":["0.000","0.000"],"namesDist":["0.000","0.000"],"titlePosY":"0.000","titleRotY":"0.000","titleDist":"0.000"}]},{"title":"NHT’22: Narrative and Hypertext 2022","author":["Charlie Hargood","David Millard"],"year":"2022","type":"short","source":"./_ref/htconference/2022/3511095.3532576.html","customData":[{"isFavorite":false,"keywords":["Narrative","Hypertext","Digital Storytelling","Authoring Tools","Narrative Games","Interactive Narrative"],"keywordsPosY":["0.000","0.000","0.000","0.000","0.000","0.000"],"keywordsRotY":["0.000","0.000","0.000","0.000","0.000","0.000"],"keywordsDist":["0.000","0.000","0.000","0.000","0.000","0.000"],"names":["Charlie Hargood","David Millard"],"namesPosY":["0.000","0.000"],"namesRotY":["0.000","0.000"],"namesDist":["0.000","0.000"],"titlePosY":"0.000","titleRotY":"0.000","titleDist":"0.000"}]},{"title":"Revealing the Demographic Attributes of the Authors from the Abstracts of Scientific Articles","author":["Salim Sazzed"],"year":"2022","type":"long","source":"./_ref/htconference/2022/3511095.3536358.html","customData":[{"isFavorite":false,"keywords":["demography prediction","native language identification","scientific publication","gender prediction","peer review","article abstract","authorship attribution"],"keywordsPosY":["0.000","0.000","0.000","0.000","0.000","0.000","0.000"],"keywordsRotY":["0.000","0.000","0.000","0.000","0.000","0.000","0.000"],"keywordsDist":["0.000","0.000","0.000","0.000","0.000","0.000","0.000"],"names":["Salim Sazzed"],"namesPosY":["0.000"],"namesRotY":["0.000"],"namesDist":["0.000"],"titlePosY":"0.000","titleRotY":"0.000","titleDist":"0.000"}]},{"title":"Robust metadata in multiple environments","author":["Frode Hegland"],"year":"2022","type":"long","source":"./_ref/htconference/2022/3511095.3536360.html","customData":[{"isFavorite":false,"keywords":["Metadata","document","infrastructure VR","AR","physical media","Visual-Meta","Metaverse"],"keywordsPosY":["0.000","0.000","0.000","0.000","0.000","0.000","0.000"],"keywordsRotY":["0.000","0.000","0.000","0.000","0.000","0.000","0.000"],"keywordsDist":["0.000","0.000","0.000","0.000","0.000","0.000","0.000"],"names":["Frode Hegland"],"namesPosY":["0.000"],"namesRotY":["0.000"],"namesDist":["0.000"],"titlePosY":"0.000","titleRotY":"0.000","titleDist":"0.000"}]},{"title":"From Users to (Sense)Makers: On the Pivotal Role of Stigmergic Social Annotation in the Quest for Collective Sensemaking","author":["Ronen Tamari","Daniel Friedman","William Fischer","Lauren Hebert","Dafna Shahaf"],"year":"2022","type":"poster","source":"./_ref/htconference/2022/3511095.3536361.html","customData":[{"isFavorite":false,"keywords":["web","environment","global","online","societies","crises","centralized","platforms","pollution","decentralization","open source software","socio-technical","human","ecosystem","stigmergic","digital"],"keywordsPosY":["0.000","0.000","0.000","0.000","0.000","0.000","0.000","0.000","0.000","0.000","0.000","0.000","0.000","0.000","0.000","0.000"],"keywordsRotY":["0.000","0.000","0.000","0.000","0.000","0.000","0.000","0.000","0.000","0.000","0.000","0.000","0.000","0.000","0.000","0.000"],"keywordsDist":["0.000","0.000","0.000","0.000","0.000","0.000","0.000","0.000","0.000","0.000","0.000","0.000","0.000","0.000","0.000","0.000"],"names":["Ronen Tamari","Daniel Friedman","William Fischer","Lauren Hebert","Dafna Shahaf"],"namesPosY":["0.000","0.000","0.000","0.000","0.000"],"namesRotY":["0.000","0.000","0.000","0.000","0.000"],"namesDist":["0.000","0.000","0.000","0.000","0.000"],"titlePosY":"0.000","titleRotY":"0.000","titleDist":"0.000"}]},{"title":"Rites de Passage: Elucidating Displacement to Emplacement of Refugees on Twitter","author":["Aparup Khatua","Wolfgang Nejdl"],"year":"2022","type":"short","source":"./_ref/htconference/2022/3511095.3536362.html","customData":[{"isFavorite":false,"keywords":["Refugee Journey","Social Media","Twitter","Multimodal Framework","2022 Ukrainian Refugee Crisis"],"keywordsPosY":["0.000","0.000","0.000","0.000","0.000"],"keywordsRotY":["0.000","0.000","0.000","0.000","0.000"],"keywordsDist":["0.000","0.000","0.000","0.000","0.000"],"names":["Aparup Khatua","Wolfgang Nejdl"],"namesPosY":["0.000","0.000"],"namesRotY":["0.000","0.000"],"namesDist":["0.000","0.000"],"titlePosY":"0.000","titleRotY":"0.000","titleDist":"0.000"}]},{"title":"Emotional Closeness by Means of Intelligent Thoughts and Memory Spaces","author":["Claus Atzenbeck","Mark Bernstein","Sarah Diefenbach"],"year":"2022","type":"long","source":"./_ref/htconference/2022/3511095.3536363.html","customData":[{"isFavorite":false,"keywords":["emotional closeness","memory space","remembrances","collective memory","family memory","intergenerational","storytelling","long-distance relationships","hypertext"],"keywordsPosY":["0.000","0.000","0.000","0.000","0.000","0.000","0.000","0.000","0.000"],"keywordsRotY":["0.000","0.000","0.000","0.000","0.000","0.000","0.000","0.000","0.000"],"keywordsDist":["0.000","0.000","0.000","0.000","0.000","0.000","0.000","0.000","0.000"],"names":["Claus Atzenbeck","Mark Bernstein","Sarah Diefenbach"],"namesPosY":["0.000","0.000","0.000"],"namesRotY":["0.000","0.000","0.000"],"namesDist":["0.000","0.000","0.000"],"titlePosY":"0.000","titleRotY":"0.000","titleDist":"0.000"}]},{"title":"Impact of Exogenous Biases of Instagram Posts on Park Visitation Estimation","author":["Afra Mashhadi","Sana Suse","Susan Ammiri","Spencer Wood"],"year":"2022","type":"long","source":"./_ref/htconference/2022/3511095.3536364.html","customData":[{"isFavorite":false,"keywords":["social media","decision-making","urban computing","smart cities","management","public parks","data","biases","longitudinal study","pandemic"],"keywordsPosY":["0.000","0.000","0.000","0.000","0.000","0.000","0.000","0.000","0.000","0.000"],"keywordsRotY":["0.000","0.000","0.000","0.000","0.000","0.000","0.000","0.000","0.000","0.000"],"keywordsDist":["0.000","0.000","0.000","0.000","0.000","0.000","0.000","0.000","0.000","0.000"],"names":["Afra Mashhadi","Sana Suse","Susan Ammiri","Spencer Wood"],"namesPosY":["0.000","0.000","0.000","0.000"],"namesRotY":["0.000","0.000","0.000","0.000"],"namesDist":["0.000","0.000","0.000","0.000"],"titlePosY":"0.000","titleRotY":"0.000","titleDist":"0.000"}]},{"title":"The Web At War: Hypertext, Social Media, and Totalitarianism","author":["Mark Bernstein"],"year":"2022","type":"long","source":"./_ref/htconference/2022/3511095.3536365.html","customData":[{"isFavorite":false,"keywords":["Hypertext","Social Media","Politics","War"],"keywordsPosY":["0.000","0.000","0.000","0.000"],"keywordsRotY":["0.000","0.000","0.000","0.000"],"keywordsDist":["0.000","0.000","0.000","0.000"],"names":["Mark Bernstein"],"namesPosY":["0.000"],"namesRotY":["0.000"],"namesDist":["0.000"],"titlePosY":"0.000","titleRotY":"0.000","titleDist":"0.000"}]},{"title":"Exploring Semantically Interlaced Cultural Heritage Narratives","author":["Noemi Mauro","Angelo Geninatti Cossatin","Ester Cravero","Liliana Ardissono","Guido Magnano","Marco Giardino"],"year":"2022","type":"short","source":"./_ref/htconference/2022/3511095.3536366.html","customData":[{"isFavorite":false,"keywords":["hypertext models","mobile guides","Cultural Heritage"],"keywordsPosY":["0.000","0.000","0.000"],"keywordsRotY":["0.000","0.000","0.000"],"keywordsDist":["0.000","0.000","0.000"],"names":["Afra Mashhadi","Sana Suse","Susan Ammiri","Spencer Wood"],"namesPosY":["0.000","0.000","0.000","0.000"],"namesRotY":["0.000","0.000","0.000","0.000"],"namesDist":["0.000","0.000","0.000","0.000"],"titlePosY":"0.000","titleRotY":"0.000","titleDist":"0.000"}]},{"title":"Identifying neutral reviews from unlabeled data: An exploratory study on user ratings and word-level polarity scores","author":["Salim Sazzed"],"year":"2022","type":"workshop","source":"./_ref/htconference/2022/3511095.3536367.html","customData":[{"isFavorite":false,"keywords":["neutral review","unlabeled data","sentiment analysis","sentiment lexicon","context sensitivity"],"keywordsPosY":["0.000","0.000","0.000","0.000","0.000"],"keywordsRotY":["0.000","0.000","0.000","0.000","0.000"],"keywordsDist":["0.000","0.000","0.000","0.000","0.000"],"names":["Salim Sazzed"],"namesPosY":["0.000"],"namesRotY":["0.000"],"namesDist":["0.000"],"titlePosY":"0.000","titleRotY":"0.000","titleDist":"0.000"}]},{"title":"Erasing Labor with Labor: Dark Patterns and Lockstep Behaviors on Google Play","author":["Ashwin Singh","Arvindh Arun","Pulak Malhotra","Pooja Desur","Ayushi Jain","Duen Horng Chau","Ponnurangam Kumaraguru"],"year":"2022","type":"short","source":"./_ref/htconference/2022/3511095.3536368.html","customData":[{"isFavorite":false,"keywords":["Google Play","Dark Patterns","Fraud"],"keywordsPosY":["0.000","0.000","0.000"],"keywordsRotY":["0.000","0.000","0.000"],"keywordsDist":["0.000","0.000","0.000"],"names":["Ashwin Singh","Arvindh Arun","Pulak Malhotra","Pooja Desur","Ayushi Jain","Duen Horng Chau","Ponnurangam Kumaraguru"],"namesPosY":["0.000","0.000","0.000","0.000","0.000","0.000","0.000"],"namesRotY":["0.000","0.000","0.000","0.000","0.000","0.000","0.000"],"namesDist":["0.000","0.000","0.000","0.000","0.000","0.000","0.000"],"titlePosY":"0.000","titleRotY":"0.000","titleDist":"0.000"}]},{"title":"Personalized Interventions for Online Moderation","author":["Stefano Cresci","Amaury Trujillo","Tiziano Fagni"],"year":"2022","type":"poster","source":"./_ref/htconference/2022/3511095.3536369.html","customData":[{"isFavorite":false,"keywords":["online moderation","moderation interventions","personalization","user modeling","social media"],"keywordsPosY":["0.000","0.000","0.000","0.000","0.000"],"keywordsRotY":["0.000","0.000","0.000","0.000","0.000"],"keywordsDist":["0.000","0.000","0.000","0.000","0.000"],"names":["Stefano Cresci","Amaury Trujillo","Tiziano Fagni"],"namesPosY":["0.000","0.000","0.000"],"namesRotY":["0.000","0.000","0.000"],"namesDist":["0.000","0.000","0.000"],"titlePosY":"0.000","titleRotY":"0.000","titleDist":"0.000"}]},{"title":"More Comfortable With Chaos: Using Hypertext to Shatter Echo Chambers and Promote Creativity","author":["Dana McKay","Stephann Makri","George Buchanan"],"year":"2022","type":"workshop","source":"./_ref/htconference/2022/3511095.3536371.html","customData":[{"isFavorite":false,"keywords":["Chaos","Serendipity","Creativity","Information Behaviour","Search","Hypertext"],"keywordsPosY":["0.000","0.000","0.000","0.000","0.000","0.000"],"keywordsRotY":["0.000","0.000","0.000","0.000","0.000","0.000"],"keywordsDist":["0.000","0.000","0.000","0.000","0.000","0.000"],"names":["Dana McKay","Stephann Makri","George Buchanan"],"namesPosY":["0.000","0.000","0.000"],"namesRotY":["0.000","0.000","0.000"],"namesDist":["0.000","0.000","0.000"],"titlePosY":"0.000","titleRotY":"0.000","titleDist":"0.000"}]},{"title":"Weaponising Social Media for Information Divide and Warfare","author":["Ehsan-Ul Haq","Gareth Tyson","Tristan Braud","Pan Hui"],"year":"2022","type":"long","source":"./_ref/htconference/2022/3511095.3536372.html","customData":[{"isFavorite":false,"keywords":["Online Social Networks","Crisis","Information Warfare","Information Divide"],"keywordsPosY":["0.000","0.000","0.000","0.000"],"keywordsRotY":["0.000","0.000","0.000","0.000"],"keywordsDist":["0.000","0.000","0.000","0.000"],"names":["Ehsan-Ul Haq","Gareth Tyson","Tristan Braud","Pan Hui"],"namesPosY":["0.000","0.000","0.000","0.000"],"namesRotY":["0.000","0.000","0.000","0.000"],"namesDist":["0.000","0.000","0.000","0.000"],"titlePosY":"0.000","titleRotY":"0.000","titleDist":"0.000"}]},{"title":"Hyperownership: Beyond the Current State of Interaction with Digital Property","author":["Amaury Trujillo"],"year":"2022","type":"short","source":"./_ref/htconference/2022/3511095.3536373.html","customData":[{"isFavorite":false,"keywords":["digital ownership","distributed ledger technology","non-fungible tokens"],"keywordsPosY":["0.000","0.000","0.000"],"keywordsRotY":["0.000","0.000","0.000"],"keywordsDist":["0.000","0.000","0.000"],"names":["Amaury Trujillo"],"namesPosY":["0.000"],"namesRotY":["0.000"],"namesDist":["0.000"],"titlePosY":"0.000","titleRotY":"0.000","titleDist":"0.000"}]},{"title":"Telegram Monitor: Monitoring Brazilian Political Groups and Channels on Telegram","author":["Manoel Júnior","Philipe Melo","Daniel Kansaon","Vitor Mafra","Kaio Sa","Fabricio Benevenuto"],"year":"2022","type":"short","source":"./_ref/htconference/2022/3511095.3536375.html","customData":[{"isFavorite":false,"keywords":["Telegram","instant messaging platforms","misinformation","fake news","politics"],"keywordsPosY":["0.000","0.000","0.000","0.000","0.000"],"keywordsRotY":["0.000","0.000","0.000","0.000","0.000"],"keywordsDist":["0.000","0.000","0.000","0.000","0.000"],"names":["Manoel Júnior","Philipe Melo","Daniel Kansaon","Vitor Mafra","Kaio Sa","Fabricio Benevenuto"],"namesPosY":["0.000","0.000","0.000","0.000","0.000","0.000"],"namesRotY":["0.000","0.000","0.000","0.000","0.000","0.000"],"namesDist":["0.000","0.000","0.000","0.000","0.000","0.000"],"titlePosY":"0.000","titleRotY":"0.000","titleDist":"0.000"}]},{"title":"EarlyAd: A System for Real-Time Surveillance of Brazilian Early Electoral Ads on Twitter","author":["Marcelo M. R. Araújo","Samuel Guimarães","Marcio Silva","Josemar Caetano","Jonatas Santos","Julio C. S. Reis","Ana P. C. Silva","Fabricio Benevenuto","Jussara M. Almeida"],"year":"2022","type":"long","source":"./_ref/htconference/2022/3511095.3536376.html","customData":[{"isFavorite":false,"keywords":["Twitter","Politics","Early Electoral Ads","Political Advertisement","Propaganda"],"keywordsPosY":["0.000","0.000","0.000","0.000","0.000"],"keywordsRotY":["0.000","0.000","0.000","0.000","0.000"],"keywordsDist":["0.000","0.000","0.000","0.000","0.000"],"names":["Marcelo M. R. Araújo","Samuel Guimarães","Marcio Silva","Josemar Caetano","Jonatas Santos","Julio C. S. Reis","Ana P. C. Silva","Fabricio Benevenuto","Jussara M. Almeida"],"namesPosY":["0.000","0.000","0.000","0.000","0.000","0.000","0.000","0.000","0.000"],"namesRotY":["0.000","0.000","0.000","0.000","0.000","0.000","0.000","0.000","0.000"],"namesDist":["0.000","0.000","0.000","0.000","0.000","0.000","0.000","0.000","0.000"],"titlePosY":"0.000","titleRotY":"0.000","titleDist":"0.000"}]},{"title":"Understanding Effects of Moderation and Migration on Online Video Sharing Platforms","author":["Gabriel Luis Santos Freire","Tales Panoutsos","Lucas Perez","Fabricio Benevenuto","Flavio Figueiredo"],"year":"2022","type":"long","source":"./_ref/htconference/2022/3511095.3536377.html","customData":[{"isFavorite":false,"keywords":["misinformation","content moderation","video platform","youtube","regression discontinuity","fake news"],"keywordsPosY":["0.000","0.000","0.000","0.000","0.000","0.000"],"keywordsRotY":["0.000","0.000","0.000","0.000","0.000","0.000"],"keywordsDist":["0.000","0.000","0.000","0.000","0.000","0.000"],"names":["Gabriel Luis Santos Freire","Tales Panoutsos","Lucas Perez","Fabricio Benevenuto","Flavio Figueiredo"],"namesPosY":["0.000","0.000","0.000","0.000","0.000"],"namesRotY":["0.000","0.000","0.000","0.000","0.000"],"namesDist":["0.000","0.000","0.000","0.000","0.000"],"titlePosY":"0.000","titleRotY":"0.000","titleDist":"0.000"}]}],"saveState":[{"type":"boxpreview","yPos":-1.144749907706493,"yRot":5.219979507584677,"docindex":3},{"type":"document","yPos":0.9621485231929747,"yRot":-0.3157136847261429,"docindex":2,"dist":3.2604480805759795,"scroll":0.19280519675058116,"botPos":-3.7730783185790866},{"type":"document","yPos":0,"yRot":-1.051984949383169,"docindex":23,"dist":3.2070511310115255,"scroll":0,"botPos":-0.6563782170617014,"highlights":[]},{"type":"refpreview","yPos":1.021022473320628,"yRot":-0.9821607174057896,"title":"The Future of Text","author":"Frode Hegland (Ed.)","year":2020,"source":"https://doi.org/10.48197/fot2020a","zdistance":3.1971024324301824,"parentTitle":"Robust metadata in multiple environments"},{"type":"boxmenu","yPos":-0.3129178523653433,"yRot":0.19350250075966002,"active":"all"}],"savedOn":"2024-11-23T0:0:00.000Z"}